examples
jjb
reliabilly
