Metadata-Version: 1.2
Name: reliabilly
Version: 2019.1.230034
Summary: Python common types for reliable microservice development.
Home-page: UNKNOWN
Author: Corpseware
Author-email: jblouse@corpseware.com
License: MIT
Platform: UNKNOWN
Requires-Python: ~=3.6
